AUTHORS
CHANGES.md
LICENSE
MANIFEST.in
README.rst
setup.py
MICC.egg-info/PKG-INFO
MICC.egg-info/SOURCES.txt
MICC.egg-info/dependency_links.txt
MICC.egg-info/requires.txt
MICC.egg-info/top_level.txt
micc/MICC.py
micc/__init__.py
micc/cgraph.py
micc/cli.py
micc/curvepair.py
micc/curves.py
micc/graph.py
micc/johnson.py
micc/pgraph.py
micc/setup.py
micc/tests/__init__.py
micc/tests/driver.py
micc/tests/profiler.py
micc/tests/test_distance.py
micc/tests/test_recursive_distance.py