Metadata-Version: 1.1
Name: MICC
Version: 0.1.5
Summary: An implementation of the Birman-Margalit-Menasco Theorem, to be used in a experimental, exploratory manner.
Home-page: http://micc.github.io
Author: Matt Morse, Paul Glenn
Author-email: mjmorse@buffalo.edu, paulglen@berkeley.edu
License: LICENSE
Download-URL: https://github.com/micc/micc
Platform: UNKNOWN
